nonebot_plugin_gold_price/__init__.py
nonebot_plugin_gold_price/config.py
nonebot_plugin_gold_price/gold_price.py
nonebot_plugin_gold_price-0.1.9.dist-info/licenses/LICENSE
nonebot_plugin_gold_price-0.1.9.dist-info/METADATA
nonebot_plugin_gold_price-0.1.9.dist-info/WHEEL
nonebot_plugin_gold_price-0.1.9.dist-info/top_level.txt
nonebot_plugin_gold_price-0.1.9.dist-info/RECORD
