Metadata-Version: 2.4
Name: nonebot-plugin-gold-price
Version: 0.1.9
Summary: 用于查询实时金价、绘制历史金价的NoneBot2插件
Author-email: newcovid <280310454@qq.com>
License: GPL-3.0
Project-URL: Homepage, https://github.com/newcovid/nonebot-plugin-gold-price
Project-URL: Documentation, https://github.com/newcovid/nonebot-plugin-gold-price#readme
Keywords: nonebot,gold,finance,analysis
Requires-Python: >=3.9
License-File: LICENSE
Requires-Dist: nonebot2>=2.3.0
Requires-Dist: nonebot-adapter-onebot>=2.3.0
Requires-Dist: aiohttp>=3.8.0
Requires-Dist: matplotlib>=3.6.0
Requires-Dist: nonebot-plugin-apscheduler>=0.3.0
Requires-Dist: nonebot-plugin-localstore>=0.7.0
Requires-Dist: pydantic>=1.10.0
Dynamic: license-file
